highway_circutbreaker/__init__.py
highway_circutbreaker/backoff.py
highway_circutbreaker/buffer.py
highway_circutbreaker/circuit_breaker.py
highway_circutbreaker/exceptions.py
highway_circutbreaker/failsafe.py
highway_circutbreaker/policy.py
highway_circutbreaker/py.typed
highway_circutbreaker/retry.py
highway_circutbreaker-1.0.1.dist-info/METADATA
highway_circutbreaker-1.0.1.dist-info/WHEEL
highway_circutbreaker-1.0.1.dist-info/top_level.txt
highway_circutbreaker-1.0.1.dist-info/RECORD
