Metadata-Version: 2.4
Name: highway_circutbreaker
Version: 1.0.1
Summary: A circuit breaker and retry library for handling failures in Python applications
Author-email: Your Name <your.email@example.com>
License: MIT
Project-URL: Homepage, https://github.com/rodmena-limited/highway_circutbreaker
Project-URL: Repository, https://github.com/rodmena-limited/highway_circutbreaker
Classifier: Development Status :: 4 - Beta
Classifier: Intended Audience :: Developers
Classifier: License :: OSI Approved :: MIT License
Classifier: Programming Language :: Python :: 3
Classifier: Programming Language :: Python :: 3.8
Classifier: Programming Language :: Python :: 3.9
Classifier: Programming Language :: Python :: 3.10
Classifier: Programming Language :: Python :: 3.11
Classifier: Programming Language :: Python :: 3.12
Requires-Python: >=3.9
Requires-Dist: typing-extensions>=4.0.0
Provides-Extra: dev
Requires-Dist: black>=23.0.0; extra == "dev"
Requires-Dist: isort>=5.0.0; extra == "dev"
Requires-Dist: mypy>=1.0.0; extra == "dev"
Requires-Dist: pytest>=7.0.0; extra == "dev"
Requires-Dist: pytest-mock>=3.0.0; extra == "dev"
Requires-Dist: ruff>=0.1.0; extra == "dev"
